taskengine/__init__.py
taskengine/admin.py
taskengine/api.py
taskengine/apps.py
taskengine/models.py
taskengine/tasks.py
taskengine/tests.py
taskengine/views.py
taskengine-0.0.2.dist-info/METADATA
taskengine-0.0.2.dist-info/RECORD
taskengine-0.0.2.dist-info/WHEEL
taskengine-0.0.2.dist-info/top_level.txt
