Metadata-Version: 2.1
Name: taskengine
Version: 0.0.2
Summary: TaskEngine for ProcessEngine
Home-page: https://github.com/SchoolOrchestration/ProcessEngineV2/tree/master/taskengine
Author: AppointmentGuru
Author-email: tech@appointmentguru.co
License: UNKNOWN
Platform: UNKNOWN
Classifier: Programming Language :: Python :: 3
Classifier: Operating System :: OS Independent
